Q8 - Sequence Detector/mealy/mealy.v
module sequence_mealy(
    input clk,
    input rst,
    input serial_in,
    output reg detected
);
    localparam S0 = 2'b00;
    localparam S1 = 2'b01;
    localparam S2 = 2'b10;
    localparam S3 = 2'b11;
    

    reg [1:0] state, nextstate;

    always @(posedge clk) begin
        if(rst) begin
            state <= S0;
        end
        else begin
            state <= nextstate;
        end
    end

    always @(*) begin
        case (state)
            S0 : begin
                if(serial_in) begin
                    nextstate = S1;
                    detected = 0;
                end
                else begin
                    nextstate = S0;
                    detected = 0;
                end
            end
            S1 : begin
                if(serial_in) begin
                    nextstate = S1;
                    detected = 0;
                end
                else begin
                    nextstate = S2;
                    detected = 0;
                end
            end
            S2 : begin
                if(serial_in) begin
                    nextstate = S3;
                    detected = 0;
                end
                else begin
                    nextstate = S0;
                    detected = 0;
                end
            end
            S3 : begin
                if(serial_in) begin
                    nextstate = S0;
                    detected = 1;
                end
                else begin
                    nextstate = S2;
                    detected = 0;
                end
            end
            
            default: begin
                nextstate = S0;
                detected = 0;
            end


        endcase
    end

endmodule



// testbench
module mealytb;
    reg clk;
    reg rst;
    reg serial_in;
    wire detected;

    sequence_mealy uut(.clk(clk), .rst(rst), .serial_in(serial_in), .detected(detected));

    always begin
        #5;
        clk = ~clk;
    end

    initial begin
        $dumpfile("sequence_sim.vcd");
        $dumpvars(0, mealytb);
        

        clk = 0;
        rst = 1;
        serial_in = 0;

        #5;
        rst = 0;
        serial_in = 1;
        $display("Time : %0t | Serial_Inp : %b | Detected = %b", $time, serial_in, detected);
        #10;
        serial_in = 1;
        $display("Time : %0t | Serial_Inp : %b | Detected = %b", $time, serial_in, detected);
        #10;
        serial_in = 0;
        $display("Time : %0t | Serial_Inp : %b | Detected = %b", $time, serial_in, detected);
        #10;
        serial_in = 1;
        $display("Time : %0t | Serial_Inp : %b | Detected = %b", $time, serial_in, detected);
        #10;
        serial_in = 1;
        $display("Time : %0t | Serial_Inp : %b | Detected = %b", $time, serial_in, detected);
        #10;
        serial_in = 1;
        $display("Time : %0t | Serial_Inp : %b | Detected = %b", $time, serial_in, detected);
        #10;
        serial_in = 0;
        $display("Time : %0t | Serial_Inp : %b | Detected = %b", $time, serial_in, detected);
        #10;
        serial_in = 1;
        $display("Time : %0t | Serial_Inp : %b | Detected = %b", $time, serial_in, detected);
        #10;
        serial_in = 1;
        $display("Time : %0t | Serial_Inp : %b | Detected = %b", $time, serial_in, detected);
        #10;
        serial_in =0;
        $display("Time : %0t | Serial_Inp : %b | Detected = %b", $time, serial_in, detected);
        #10;
        serial_in = 1;
        $display("Time : %0t | Serial_Inp : %b | Detected = %b", $time, serial_in, detected);
        #10;
        serial_in = 1;
        $display("Time : %0t | Serial_Inp : %b | Detected = %b", $time, serial_in, detected);
        #10;
        serial_in = 0;
        $display("Time : %0t | Serial_Inp : %b | Detected = %b", $time, serial_in, detected);
        #10;
        serial_in = 1;
        $display("Time : %0t | Serial_Inp : %b | Detected = %b", $time, serial_in, detected);
        $finish;
    end

endmodule

Q8 - Sequence Detector/mealy/sequence_sim.vcd
$date
	Thu Jun 18 08:15:37 2026
$end
$version
	Icarus Verilog
$end
$timescale
	1s
$end
$scope module mealytb $end
$var wire 1 ! detected $end
$var reg 1 " clk $end
$var reg 1 # rst $end
$var reg 1 $ serial_in $end
$scope module uut $end
$var wire 1 " clk $end
$var wire 1 # rst $end
$var wire 1 $ serial_in $end
$var parameter 2 % S0 $end
$var parameter 2 & S1 $end
$var parameter 2 ' S2 $end
$var parameter 2 ( S3 $end
$var reg 1 ! detected $end
$var reg 2 ) nextstate [1:0] $end
$var reg 2 * state [1:0] $end
$upscope $end
$upscope $end
$enddefinitions $end
$comment Show the parameter values. $end
$dumpall
b11 (
b10 '
b1 &
b0 %
$end
#0
$dumpvars
bx *
b0 )
0$
1#
0"
0!
$end
#5
b1 )
b0 *
1$
0#
1"
#10
0"
#15
b1 *
1"
#20
0"
#25
b10 *
b0 )
1"
0$
#30
0"
#35
1!
b11 *
b0 )
1"
1$
#40
0"
#45
0!
b1 )
b0 *
1"
#50
0"
#55
b1 *
1"
#60
0"
#65
b10 *
b0 )
1"
0$
#70
0"
#75
1!
b11 *
b0 )
1"
1$
#80
0"
#85
0!
b1 )
b0 *
1"
#90
0"
#95
b0 )
1"
0$
#100
0"
#105
b1 *
b1 )
1"
1$
#110
0"
#115
1"
#120
0"
#125
b10 *
b0 )
1"
0$
#130
0"
#135
1!
b11 *
b0 )
1"
1$
