Q8 - Sequence Detector/moore/moore.v
`timescale 1ns/1ns
// detecting the sequence overlapping 1011


// MOORE MACHINE
module sequence_moore(
    input clk,
    input rst,
    input serial_in,
    output reg detected
);

    localparam S0 = 3'b000;
    localparam S1 = 3'b001;
    localparam S2 = 3'b010;
    localparam S3 = 3'b011;
    localparam S4 = 3'b100;
    
    reg [2:0] state, nextstate;

    always @(posedge clk) begin
        if(rst) begin
            state <= S0;
        end
        else begin
            state <= nextstate;
        end
    end



    always @(*) begin
        case (state) 
            S0 : begin
                if(serial_in) begin
                    nextstate = S1;
                end
                else begin
                    nextstate = S0;
                end
            end

            S1 : begin
                if(serial_in) begin
                    nextstate = S1;
                end
                else begin
                    nextstate = S2;
                end
            end

            S2: begin
                if(serial_in) begin
                    nextstate = S3;
                end
                else begin
                    nextstate = S0;
                end
            end
            S3: begin
                if(serial_in) begin
                    nextstate = S4;
                end
                else begin
                    nextstate = S2;
                end
            end
            S4 : begin
                if(serial_in) begin
                    nextstate = S1;
                end
                else begin
                    nextstate = S2;
                end
            end
            default: begin
                nextstate = S0;
            end
    
        endcase
    end
    
    // Moore Logic
    always @(*) begin
        if(state == S4) begin
            detected = 1;
        end
        else begin 
            detected = 0;
        end
    end

endmodule



// testbench
module mooretb;
    reg clk;
    reg rst;
    reg serial_in;
    wire detected;

    sequence_moore uut(.clk(clk), .rst(rst), .serial_in(serial_in), .detected(detected));

    always begin
        #5;
        clk = ~clk;
    end

    initial begin
        $dumpfile("sequence_sim.vcd");
        $dumpvars(0, mooretb);
        

        clk = 0;
        rst = 1;
        serial_in = 0;

        #5;
        rst = 0;
        serial_in = 1;
        $display("Time : %0t | Serial_Inp : %b | Detected = %b", $time, serial_in, detected);
        #10;
        serial_in = 1;
        $display("Time : %0t | Serial_Inp : %b | Detected = %b", $time, serial_in, detected);
        #10;
        serial_in = 0;
        $display("Time : %0t | Serial_Inp : %b | Detected = %b", $time, serial_in, detected);
        #10;
        serial_in = 1;
        $display("Time : %0t | Serial_Inp : %b | Detected = %b", $time, serial_in, detected);
        #10;
        serial_in = 1;
        $display("Time : %0t | Serial_Inp : %b | Detected = %b", $time, serial_in, detected);
        #10;
        serial_in = 1;
        $display("Time : %0t | Serial_Inp : %b | Detected = %b", $time, serial_in, detected);
        #10;
        serial_in = 0;
        $display("Time : %0t | Serial_Inp : %b | Detected = %b", $time, serial_in, detected);
        #10;
        serial_in = 1;
        $display("Time : %0t | Serial_Inp : %b | Detected = %b", $time, serial_in, detected);
        #10;
        serial_in = 1;
        $display("Time : %0t | Serial_Inp : %b | Detected = %b", $time, serial_in, detected);
        #10;
        serial_in =0;
        $display("Time : %0t | Serial_Inp : %b | Detected = %b", $time, serial_in, detected);
        #10;
        serial_in = 1;
        $display("Time : %0t | Serial_Inp : %b | Detected = %b", $time, serial_in, detected);
        #10;
        serial_in = 1;
        $display("Time : %0t | Serial_Inp : %b | Detected = %b", $time, serial_in, detected);
        #10;
        serial_in = 0;
        $display("Time : %0t | Serial_Inp : %b | Detected = %b", $time, serial_in, detected);
        #10;
        serial_in = 1;
        $display("Time : %0t | Serial_Inp : %b | Detected = %b", $time, serial_in, detected);
        $finish;
    end

endmodule

Q8 - Sequence Detector/moore/sequence_sim.vcd
$date
	Thu Jun 18 07:53:34 2026
$end
$version
	Icarus Verilog
$end
$timescale
	1ns
$end
$scope module mooretb $end
$var wire 1 ! detected $end
$var reg 1 " clk $end
$var reg 1 # rst $end
$var reg 1 $ serial_in $end
$scope module uut $end
$var wire 1 " clk $end
$var wire 1 # rst $end
$var wire 1 $ serial_in $end
$var parameter 3 % S0 $end
$var parameter 3 & S1 $end
$var parameter 3 ' S2 $end
$var parameter 3 ( S3 $end
$var parameter 3 ) S4 $end
$var reg 1 ! detected $end
$var reg 3 * nextstate [2:0] $end
$var reg 3 + state [2:0] $end
$upscope $end
$upscope $end
$enddefinitions $end
$comment Show the parameter values. $end
$dumpall
b100 )
b11 (
b10 '
b1 &
b0 %
$end
#0
$dumpvars
bx +
b0 *
0$
1#
0"
x!
$end
#5
0!
b1 *
b0 +
1$
0#
1"
#10
0"
#15
b1 +
1"
#20
0"
#25
b10 +
b0 *
1"
0$
#30
0"
#35
b11 +
b100 *
1"
1$
#40
0"
#45
1!
b1 *
b100 +
1"
#50
0"
#55
0!
b1 +
1"
#60
0"
#65
b10 +
b0 *
1"
0$
#70
0"
#75
b11 +
b100 *
1"
1$
#80
0"
#85
1!
b1 *
b100 +
1"
#90
0"
#95
0!
b10 +
b0 *
1"
0$
#100
0"
#105
b11 +
b100 *
1"
1$
#110
0"
#115
1!
b1 *
b100 +
1"
#120
0"
#125
0!
b10 +
b0 *
1"
0$
#130
0"
#135
b11 +
b100 *
1"
1$
