Q5 - Parameterised Johnson Counter/main.v
`timescale 1ns/1ns

// synchronous reset
module johnsoncounter #(parameter N = 4) (
  input wire clk,
  input wire rst,
  output reg [N-1:0] out
);
  
  always @(posedge clk) begin
    if(rst) out <= {N{1'b0}};
    else begin
      out <= {~out[0], out[N-1:1]};
    end
  end
  
endmodule



// Testbench
module johnsoncountertb;
  localparam N = 4;
  reg clk=0;
  reg rst;
  wire [N-1:0] out;
  
  johnsoncounter #(N) uut(.clk(clk), .rst(rst), .out(out));
  
  always begin
    #5;
    clk = ~clk;
  end

  
  initial begin
    $dumpfile("waveform.vcd");
    $dumpvars(0, johnsoncountertb);
    rst = 1'b1;
    $monitor("Time=%0t | rst=%b | out=%b", $time, rst, out);
    #11;
    rst = 1'b0;
    #105;
    $finish;

  end
endmodule

Q5 - Parameterised Johnson Counter/waveform.vcd
$date
	Mon Jun 15 05:46:48 2026
$end
$version
	Icarus Verilog
$end
$timescale
	1ns
$end
$scope module johnsoncountertb $end
$var wire 4 ! out [3:0] $end
$var parameter 32 " N $end
$var reg 1 # clk $end
$var reg 1 $ rst $end
$scope module uut $end
$var wire 1 # clk $end
$var wire 1 $ rst $end
$var parameter 32 % N $end
$var reg 4 & out [3:0] $end
$upscope $end
$upscope $end
$enddefinitions $end
$comment Show the parameter values. $end
$dumpall
b100 %
b100 "
$end
#0
$dumpvars
bx &
1$
0#
bx !
$end
#5
b0 !
b0 &
1#
#10
0#
#11
0$
#15
b1000 !
b1000 &
1#
#20
0#
#25
b1100 !
b1100 &
1#
#30
0#
#35
b1110 !
b1110 &
1#
#40
0#
#45
b1111 !
b1111 &
1#
#50
0#
#55
b111 !
b111 &
1#
#60
0#
#65
b11 !
b11 &
1#
#70
0#
#75
b1 !
b1 &
1#
#80
0#
#85
b0 !
b0 &
1#
#90
0#
#95
b1000 !
b1000 &
1#
#100
0#
#105
b1100 !
b1100 &
1#
#110
0#
#115
b1110 !
b1110 &
1#
