Q7 - Configurable Shift Register with Modes/main.v
`timescale 1ns/1ns

module shiftregister_config(
    input clk,
    input rst,
    input [1:0] mode,
    input sin_l,
    input sin_r,
    input [7:0] d,
    output reg [7:0] q
);



    always @(posedge clk) begin
        if(rst) begin 
            q <= 8'd0; 
        end
        else begin
            case (mode) 
                2'b00 : q <= d;
                2'b01 : q <= {d[6:0], sin_l}; 
                2'b10 : q <= {sin_r, d[7:1]};
                2'b11 : q <= d;
                default : q <= d;

            endcase
        end
    end

endmodule


// testbench
module shiftregtb;
    reg clk;
    reg rst;
    reg [1:0] mode;
    reg sin_l;
    reg sin_r;
    reg [7:0] d;
    wire [7:0] q;


    shiftregister_config uut(.clk(clk), .rst(rst), .mode(mode), .sin_l(sin_l), .sin_r(sin_r), .d(d), .q(q));

    always begin
        #5;
        clk = ~clk;
    end

    initial begin
        $dumpfile("shiftreg_sim.vcd");
        $dumpvars(0, shiftregtb);
        $monitor("TIME : %0t ns | INPUT : %b | MODE : %b | OUTPUT : %b",$realtime, d, mode, q);
        clk = 0;
        rst = 1;
        d = 8'd0;
        mode = 2'b00;
        sin_r = 0;
        sin_l = 0;

        #10;
        rst = 0;
        d = 8'b11010010;
        mode = 2'b01;
        sin_l = 1;
        sin_r = 0;
        
        #15;
        mode = 2'b10;

        #10;
        rst = 1;

        #10;
        rst = 0;
        d = 8'b00001111;
        mode = 2'b11;
        sin_l = 1;
        sin_r = 1;

        #10;
        mode = 2'b01;
        #40; 
        $finish;
    end

endmodule

Q7 - Configurable Shift Register with Modes/shiftreg_sim.vcd
$date
	Thu Jun 18 01:42:56 2026
$end
$version
	Icarus Verilog
$end
$timescale
	1ns
$end
$scope module shiftregtb $end
$var wire 8 ! q [7:0] $end
$var reg 1 " clk $end
$var reg 8 # d [7:0] $end
$var reg 2 $ mode [1:0] $end
$var reg 1 % rst $end
$var reg 1 & sin_l $end
$var reg 1 ' sin_r $end
$scope module uut $end
$var wire 1 " clk $end
$var wire 8 ( d [7:0] $end
$var wire 2 ) mode [1:0] $end
$var wire 1 % rst $end
$var wire 1 & sin_l $end
$var wire 1 ' sin_r $end
$var reg 8 * q [7:0] $end
$upscope $end
$upscope $end
$enddefinitions $end
$comment Show the parameter values. $end
$dumpall
$end
#0
$dumpvars
bx *
b0 )
b0 (
0'
0&
1%
b0 $
b0 #
0"
bx !
$end
#5
b0 !
b0 *
1"
#10
0"
1&
b1 $
b1 )
b11010010 #
b11010010 (
0%
#15
b10100101 !
b10100101 *
1"
#20
0"
#25
b1101001 !
b1101001 *
1"
b10 $
b10 )
#30
0"
#35
b0 !
b0 *
1"
1%
#40
0"
#45
b1111 !
b1111 *
1"
1'
b11 $
b11 )
b1111 #
b1111 (
0%
#50
0"
#55
b11111 !
b11111 *
1"
b1 $
b1 )
