Q6 - Synchroniser/main.v
`timescale 1ns/1ps
module synchroniser #(parameter N=4) (
    input clk,
    input rst,
    input [N-1:0] in,
    output reg [N-1:0] out
);
    reg [N-1:0] d1;

    always @(posedge clk) begin 
        if(rst) begin
            d1 <= {N{1'b0}};
            out <= d1;
        end
        else begin
            d1 <= in;
            out <= d1;
        end
    end
endmodule


// testbench module

module synctb;
    localparam N = 4;
    reg clk=0;
    reg rst;
    reg [N-1:0] in;
    wire [N-1:0] out;

    synchroniser #(N) uut(.clk(clk), .rst(rst), .in(in), .out(out));

    always begin
        #5;
        clk = ~clk;
    end

    initial begin
        $dumpfile("waveform.vcd");
        $dumpvars(0, synctb);
        rst = 1'b1;
        in = {N{1'b0}};
        $monitor("Time=%0t | rst=%b | in=%b | out=%b", $time, rst, in, out);
        #11;
        rst = 1'b0;
        #10;
        in = {N{1'b1}};
        #10;
        in = {N{1'b0}};
        #10;
        in = {N{1'b1}};
        #10;
        in = {N{1'b0}};
        #10;
        $finish;
    end
endmodule

Q6 - Synchroniser/waveform.vcd
$date
	Mon Jun 15 09:48:19 2026
$end
$version
	Icarus Verilog
$end
$timescale
	1ps
$end
$scope module synctb $end
$var wire 4 ! out [3:0] $end
$var parameter 32 " N $end
$var reg 1 # clk $end
$var reg 4 $ in [3:0] $end
$var reg 1 % rst $end
$scope module uut $end
$var wire 1 # clk $end
$var wire 4 & in [3:0] $end
$var wire 1 % rst $end
$var parameter 32 ' N $end
$var reg 4 ( d1 [3:0] $end
$var reg 4 ) out [3:0] $end
$upscope $end
$upscope $end
$enddefinitions $end
$comment Show the parameter values. $end
$dumpall
b100 '
b100 "
$end
#0
$dumpvars
bx )
bx (
b0 &
1%
b0 $
0#
bx !
$end
#5000
b0 (
1#
#10000
0#
#11000
0%
#15000
b0 !
b0 )
1#
#20000
0#
#21000
b1111 $
b1111 &
#25000
b1111 (
1#
#30000
0#
#31000
b0 $
b0 &
#35000
b1111 !
b1111 )
b0 (
1#
#40000
0#
#41000
b1111 $
b1111 &
#45000
b0 !
b0 )
b1111 (
1#
#50000
0#
#51000
b0 $
b0 &
#55000
b1111 !
b1111 )
b0 (
1#
